fs9721_utils/__init__.py
fs9721_utils/csv_logger.py
fs9721_utils/reading.py
fs9721_utils-0.0.3.dist-info/entry_points.txt
fs9721_utils-0.0.3.dist-info/LICENSE.md
fs9721_utils-0.0.3.dist-info/WHEEL
fs9721_utils-0.0.3.dist-info/METADATA
fs9721_utils-0.0.3.dist-info/RECORD
