Metadata-Version: 2.1
Name: fs9721-utils
Version: 0.0.3
Summary: Python based utilities for interacting with digital multimeters that are built on the FS9721-LP3 chipset.
License: MIT
Author: Fergus In London
Author-email: fergus@fergus.london
Requires-Python: >=3.9,<4.0
Classifier: License :: OSI Approved :: MIT License
Classifier: Programming Language :: Python :: 3
Classifier: Programming Language :: Python :: 3.10
Classifier: Programming Language :: Python :: 3.9
Requires-Dist: bitstruct (>=8.12.1,<9.0.0)
